gitlab_releases/__init__.py
gitlab_releases/apps.py
gitlab_releases/client.py
gitlab_releases/conf.py
gitlab_releases/models.py
gitlab_releases/paginator.py
gitlab_releases/parser.py
gitlab_releases/urls.py
gitlab_releases/utils.py
gitlab_releases/views.py
gitlab_releases-0.2.1.dist-info/licenses/LICENSE
gitlab_releases-0.2.1.dist-info/METADATA
gitlab_releases-0.2.1.dist-info/WHEEL
gitlab_releases-0.2.1.dist-info/top_level.txt
gitlab_releases-0.2.1.dist-info/RECORD
