Metadata-Version: 2.4
Name: gitlab-releases
Version: 0.2.1
Summary: Gitlab Releases for Django projects
Author-email: Valberto Carneiro <valbertovc@gmail.com>
License-Expression: MIT
Project-URL: Changelog, https://github.com/valbertovc/gitlab-releases/releases
Project-URL: Repository, https://github.com/valbertovc/gitlab-releases
Project-URL: Documentation, https://gitlab-releases.readthedocs.io/en/latest/
Keywords: Django,Gitlab,Releases
Classifier: Development Status :: 4 - Beta
Classifier: Framework :: Django :: 3
Classifier: Framework :: Django :: 3.2
Classifier: Framework :: Django :: 4
Classifier: Framework :: Django :: 4.1
Classifier: Framework :: Django :: 5
Classifier: Framework :: Django :: 5.1
Classifier: Framework :: Django :: 5.2
Classifier: Intended Audience :: Developers
Classifier: Operating System :: OS Independent
Classifier: Programming Language :: Python
Classifier: Programming Language :: Python :: 3
Classifier: Programming Language :: Python :: 3.9
Classifier: Programming Language :: Python :: 3.10
Classifier: Programming Language :: Python :: 3.11
Classifier: Programming Language :: Python :: 3.12
Classifier: Programming Language :: Python :: 3.13
Classifier: Topic :: Software Development :: Libraries :: Application Frameworks
Requires-Python: <3.14,>=3.9
License-File: LICENSE
Requires-Dist: django<6,>=3
Requires-Dist: python-gitlab>=6.5.0
Dynamic: license-file
